common_grants_sdk/__init__.py
common_grants_sdk/schemas/__init__.py
common_grants_sdk/schemas/marshmallow/__init__.py
common_grants_sdk/schemas/marshmallow/generated_schema.py
common_grants_sdk/schemas/pydantic/__init__.py
common_grants_sdk/schemas/pydantic/base.py
common_grants_sdk/schemas/pydantic/fields/__init__.py
common_grants_sdk/schemas/pydantic/fields/custom.py
common_grants_sdk/schemas/pydantic/fields/event.py
common_grants_sdk/schemas/pydantic/fields/metadata.py
common_grants_sdk/schemas/pydantic/fields/money.py
common_grants_sdk/schemas/pydantic/filters/__init__.py
common_grants_sdk/schemas/pydantic/filters/base.py
common_grants_sdk/schemas/pydantic/filters/date.py
common_grants_sdk/schemas/pydantic/filters/money.py
common_grants_sdk/schemas/pydantic/filters/numeric.py
common_grants_sdk/schemas/pydantic/filters/opportunity.py
common_grants_sdk/schemas/pydantic/filters/string.py
common_grants_sdk/schemas/pydantic/models/__init__.py
common_grants_sdk/schemas/pydantic/models/opp_base.py
common_grants_sdk/schemas/pydantic/models/opp_funding.py
common_grants_sdk/schemas/pydantic/models/opp_status.py
common_grants_sdk/schemas/pydantic/models/opp_timeline.py
common_grants_sdk/schemas/pydantic/pagination.py
common_grants_sdk/schemas/pydantic/requests/__init__.py
common_grants_sdk/schemas/pydantic/requests/opportunity.py
common_grants_sdk/schemas/pydantic/responses/__init__.py
common_grants_sdk/schemas/pydantic/responses/base.py
common_grants_sdk/schemas/pydantic/responses/error.py
common_grants_sdk/schemas/pydantic/responses/opportunity.py
common_grants_sdk/schemas/pydantic/responses/success.py
common_grants_sdk/schemas/pydantic/sorting.py
common_grants_sdk/schemas/pydantic/types.py
common_grants_sdk/utils/transformation.py
common_grants_sdk-0.3.2.dist-info/METADATA
common_grants_sdk-0.3.2.dist-info/WHEEL
common_grants_sdk-0.3.2.dist-info/RECORD
