Metadata-Version: 2.3
Name: common-grants-sdk
Version: 0.3.2
Summary: Python SDK for the CommonGrants protocol
Author: Your Name
Author-email: you@example.com
Requires-Python: >=3.11,<4.0
Classifier: Programming Language :: Python :: 3
Classifier: Programming Language :: Python :: 3.11
Classifier: Programming Language :: Python :: 3.12
Classifier: Programming Language :: Python :: 3.13
Requires-Dist: marshmallow (>=3.20.0,<4.0.0)
Requires-Dist: pydantic (>=2.11.0,<3.0.0)
